bazoola/__init__.py
bazoola/cond.py
bazoola/db.py
bazoola/errors.py
bazoola/fields.py
bazoola/join.py
bazoola/row.py
bazoola/storage.py
bazoola/table.py
bazoola-0.0.6.dist-info/LICENSE
bazoola-0.0.6.dist-info/METADATA
bazoola-0.0.6.dist-info/WHEEL
bazoola-0.0.6.dist-info/RECORD
