Metadata-Version: 2.3
Name: bazoola
Version: 0.0.6
Summary: A lightweight, file-based database implementation in Python
License: MIT
Keywords: database,file-based,educational,lightweight
Author: Dima Doroshev
Author-email: github@doroshev.com
Requires-Python: >=3.10,<4.0
Classifier: Development Status :: 4 - Beta
Classifier: Intended Audience :: Developers
Classifier: Intended Audience :: Education
Classifier: License :: OSI Approved :: MIT License
Classifier: Programming Language :: Python :: 3
Classifier: Programming Language :: Python :: 3.10
Classifier: Programming Language :: Python :: 3.11
Classifier: Programming Language :: Python :: 3.12
Classifier: Programming Language :: Python :: 3.13
Classifier: Topic :: Database
Classifier: Topic :: Education
Classifier: Topic :: Software Development :: Libraries :: Python Modules
Project-URL: Documentation, https://github.com/ddoroshev/bazoola#readme
Project-URL: Homepage, https://github.com/ddoroshev/bazoola
Project-URL: Repository, https://github.com/ddoroshev/bazoola
